README.md
setup.py
cmc_adb_utils.egg-info/PKG-INFO
cmc_adb_utils.egg-info/SOURCES.txt
cmc_adb_utils.egg-info/dependency_links.txt
cmc_adb_utils.egg-info/top_level.txt
features/__init__.py
features/behave/__init__.py
features/behave/lib/__init__.py
features/common/__init__.py
features/common/adb_utils.py
features/common/badb_utils.py
features/common/cmc_utils.py
features/common/log_db.py