Metadata-Version: 1.2
Name: cmc-adb-utils
Version: 0.1.0
Summary: Multi ADB connection
Home-page: UNKNOWN
Author: spektig
Author-email: ispektor92@gmail.com
License: UNKNOWN
Platform: UNKNOWN
Classifier: Programming Language :: Python :: 3
Classifier: License :: OSI Approved :: MIT License
Classifier: Operating System :: OS Independent
Requires-Python: >=3.10
